typingref/__init__.py
typingref/core.py
typingref-0.103.1.dist-info/LICENSE
typingref-0.103.1.dist-info/METADATA
typingref-0.103.1.dist-info/WHEEL
typingref-0.103.1.dist-info/RECORD
