Metadata-Version: 2.1
Name: typingref
Version: 0.103.1
Summary: Introspect Python type annotation, with ease.
License: MIT
Author: Nir
Author-email: 88795475+nrbnlulu@users.noreply.github.com
Maintainer: Nir.J Benlulu
Maintainer-email: nrbnlulu@gmail.com
Requires-Python: >=3.9,<3.13
Classifier: License :: OSI Approved :: MIT License
Classifier: Programming Language :: Python :: 3
Classifier: Programming Language :: Python :: 3.9
Classifier: Programming Language :: Python :: 3.10
Classifier: Programming Language :: Python :: 3.11
Classifier: Programming Language :: Python :: 3.12
Project-URL: Documentation, https://nrbnlulu.github.io/typingref/
Project-URL: Homepage, https://github.com/nrbnlulu/typingref
